odoo/addons/l10n_fr_account_vat_return_einvoice_generate/README.rst
odoo/addons/l10n_fr_account_vat_return_einvoice_generate/__init__.py
odoo/addons/l10n_fr_account_vat_return_einvoice_generate/__manifest__.py
odoo/addons/l10n_fr_account_vat_return_einvoice_generate/i18n/l10n_fr_account_vat_return_einvoice_generate.pot
odoo/addons/l10n_fr_account_vat_return_einvoice_generate/models/__init__.py
odoo/addons/l10n_fr_account_vat_return_einvoice_generate/models/account_move.py
odoo/addons/l10n_fr_account_vat_return_einvoice_generate/readme/CONTRIBUTORS.rst
odoo/addons/l10n_fr_account_vat_return_einvoice_generate/readme/DESCRIPTION.rst
odoo/addons/l10n_fr_account_vat_return_einvoice_generate/static/description/icon.png
odoo/addons/l10n_fr_account_vat_return_einvoice_generate/static/description/index.html
odoo_addon_l10n_fr_account_vat_return_einvoice_generate-16.0.1.0.0.2.dist-info/METADATA
odoo_addon_l10n_fr_account_vat_return_einvoice_generate-16.0.1.0.0.2.dist-info/WHEEL
odoo_addon_l10n_fr_account_vat_return_einvoice_generate-16.0.1.0.0.2.dist-info/top_level.txt
odoo_addon_l10n_fr_account_vat_return_einvoice_generate-16.0.1.0.0.2.dist-info/RECORD
