Metadata-Version: 2.1
Name: odoo-addon-l10n_fr_account_vat_return_einvoice_generate
Version: 16.0.1.0.0.2
Summary: Glue module between account_einvoice_generate and l10n_fr_account_vat_return
Home-page: https://github.com/OCA/l10n-france
Author: Akretion,Odoo Community Association (OCA)
Author-email: support@odoo-community.org
License: AGPL-3
Classifier: Programming Language :: Python
Classifier: Framework :: Odoo
Classifier: Framework :: Odoo :: 16.0
Classifier: License :: OSI Approved :: GNU Affero General Public License v3
Requires-Python: >=3.10
Requires-Dist: odoo-addon-account-einvoice-generate<16.1dev,>=16.0dev
Requires-Dist: odoo-addon-l10n-fr-account-vat-return<16.1dev,>=16.0dev
Requires-Dist: odoo<16.1dev,>=16.0a
